{"cameraMode":{"drawMode":0,"name":"Shaded","section":"Shading Mode"},"sceneLighting":true,"audioPlay":false,"sceneViewState":{"m_AlwaysRefresh":false,"showFog":true,"showSkybox":true,"showFlares":true,"showImageEffects":true,"showParticleSystems":true,"showVisualEffectGraphs":true,"m_FxEnabled":true},"in2DMode":false,"pivot":{"x":-2.928835391998291,"y":5.718181610107422,"z":-5.397125244140625},"rotation":{"x":-0.009127425029873848,"y":0.9871534705162048,"z":-0.147988423705101,"w":-0.06049344316124916},"size":14.294301986694336,"orthographic":false}