{"cameraMode":{"drawMode":0,"name":"Shaded","section":"Shading Mode"},"sceneLighting":true,"audioPlay":false,"sceneViewState":{"m_AlwaysRefresh":false,"showFog":true,"showSkybox":true,"showFlares":true,"showImageEffects":true,"showParticleSystems":true,"showVisualEffectGraphs":true,"m_FxEnabled":true},"in2DMode":false,"pivot":{"x":-1.519622802734375,"y":2.4998741149902345,"z":-29.444419860839845},"rotation":{"x":-0.0017428721766918898,"y":0.9928497076034546,"z":-0.11851818114519119,"w":-0.01459463406354189},"size":25.107830047607423,"orthographic":false}